{
  "input_file": "data/polyhedra/johnson/n34/polyhedron.grh",
  "vertices": 30,
  "edges": 60,
  "phase4": {
    "build_time_ms": 8.85,
    "count_time_ms": 1.3,
    "spanning_tree_count": "193003269869040"
  },
  "phase5": {
    "filter_applied": true,
    "num_mopes": 20,
    "subset_time_ms": 312.0,
    "non_overlapping_count": "190653702525040"
  },
  "phase6": {
    "burnside_applied": true,
    "group_order": 20,
    "burnside_time_ms": 75598.24,
    "burnside_sum": "190653740288800",
    "nonisomorphic_count": "9532687014440",
    "invariant_counts": [
      "190653702525040",
      "2029920",
      "0",
      "7146768",
      "0",
      "7146768",
      "0",
      "0",
      "0",
      "7146768",
      "0",
      "0",
      "0",
      "0",
      "7146768",
      "0",
      "0",
      "0",
      "0",
      "7146768"
    ]
  }
}